{
	"name": "Copy_From_DB_To_ADLS",
	"properties": {
		"activities": [
			{
				"name": "Copy data from sql db to data lake",
				"description": "Taking a table from my Azure SQL DB and moving it to the AWLT folder on my data lake. ",
				"type": "Copy",
				"dependsOn": [],
				"policy": {
					"timeout": "0.12:00:00",
					"retry": 0,
					"retryIntervalInSeconds": 30,
					"secureOutput": false,
					"secureInput": false
				},
				"userProperties": [],
				"typeProperties": {
					"source": {
						"type": "AzureSqlSource",
						"queryTimeout": "02:00:00",
						"partitionOption": "None"
					},
					"sink": {
						"type": "DelimitedTextSink",
						"storeSettings": {
							"type": "AzureBlobFSWriteSettings"
						},
						"formatSettings": {
							"type": "DelimitedTextWriteSettings",
							"quoteAllText": true,
							"fileExtension": ".txt"
						}
					},
					"enableStaging": false,
					"translator": {
						"type": "TabularTranslator",
						"typeConversion": true,
						"typeConversionSettings": {
							"allowDataTruncation": true,
							"treatBooleanAsNumber": false
						}
					}
				},
				"inputs": [
					{
						"referenceName": "az_sqldb_AWLT_dynamic",
						"type": "DatasetReference",
						"parameters": {
							"schema": {
								"value": "@pipeline().parameters.schema",
								"type": "Expression"
							},
							"tablename": {
								"value": "@pipeline().parameters.tablename",
								"type": "Expression"
							}
						}
					}
				],
				"outputs": [
					{
						"referenceName": "az_adls_introtoadfmm_dynamic_csv",
						"type": "DatasetReference",
						"parameters": {
							"filename": {
								"value": "@pipeline().parameters.tablename",
								"type": "Expression"
							}
						}
					}
				]
			}
		],
		"parameters": {
			"schema": {
				"type": "string"
			},
			"tablename": {
				"type": "string"
			}
		},
		"folder": {
			"name": "CopyData"
		},
		"annotations": []
	}
}